pyapidocs-0.1.1.dist-info/licenses/LICENSE.MD
src/__init__.py
src/constants.py
src/main.py
src/pyapidocs.py
pyapidocs-0.1.1.dist-info/METADATA
pyapidocs-0.1.1.dist-info/WHEEL
pyapidocs-0.1.1.dist-info/entry_points.txt
pyapidocs-0.1.1.dist-info/top_level.txt
pyapidocs-0.1.1.dist-info/RECORD
